nma_ibl/__init__.py
nma_ibl/paper_behavior_functions.py
nma_ibl/psychofit.py
nma_ibl-0.1.0.dist-info/METADATA
nma_ibl-0.1.0.dist-info/WHEEL
nma_ibl-0.1.0.dist-info/top_level.txt
nma_ibl-0.1.0.dist-info/RECORD
